{"results": [{"code": "AA2287", "data": [{"arrival": "1904", "distance": 3043, "arrival_delay": -15, "duration": 398, "number": "2287", "departure": "1526", "cancelled": 0, "carrier": "AA", "date": "2015-06-04", "departure_delay": 1}, {"arrival": "1920", "distance": 3043, "arrival_delay": 1, "duration": 420, "number": "2287", "departure": "1520", "cancelled": 0, "carrier": "AA", "date": "2015-06-05", "departure_delay": -5}, {"arrival": "1911", "distance": 3043, "arrival_delay": -8, "duration": 406, "number": "2287", "departure": "1525", "cancelled": 0, "carrier": "AA", "date": "2015-06-06", "departure_delay": 0}, {"arrival": "1924", "distance": 3043, "arrival_delay": 5, "duration": 415, "number": "2287", "departure": "1529", "cancelled": 0, "carrier": "AA", "date": "2015-06-07", "departure_delay": 4}, {"arrival": "1952", "distance": 3043, "arrival_delay": 33, "duration": 407, "number": "2287", "departure": "1605", "cancelled": 0, "carrier": "AA", "date": "2015-06-08", "departure_delay": 40}, {"arrival": "1923", "distance": 3043, "arrival_delay": 4, "duration": 412, "number": "2287", "departure": "1531", "cancelled": 0, "carrier": "AA", "date": "2015-06-09", "departure_delay": 6}, {"arrival": "1945", "distance": 3043, "arrival_delay": 26, "duration": 403, "number": "2287", "departure": "1602", "cancelled": 0, "carrier": "AA", "date": "2015-06-10", "departure_delay": 37}, {"arrival": "1904", "distance": 3043, "arrival_delay": -15, "duration": 397, "number": "2287", "departure": "1527", "cancelled": 0, "carrier": "AA", "date": "2015-06-11", "departure_delay": 2}, {"arrival": "1938", "distance": 3043, "arrival_delay": 19, "duration": 431, "number": "2287", "departure": "1527", "cancelled": 0, "carrier": "AA", "date": "2015-06-12", "departure_delay": 2}, {"arrival": "1927", "distance": 3043, "arrival_delay": 8, "duration": 400, "number": "2287", "departure": "1547", "cancelled": 0, "carrier": "AA", "date": "2015-06-13", "departure_delay": 22}, {"arrival": "1842", "distance": 3043, "arrival_delay": -37, "duration": 379, "number": "2287", "departure": "1523", "cancelled": 0, "carrier": "AA", "date": "2015-06-14", "departure_delay": -2}, {"arrival": "1935", "distance": 3043, "arrival_delay": 16, "duration": 398, "number": "2287", "departure": "1557", "cancelled": 0, "carrier": "AA", "date": "2015-06-15", "departure_delay": 32}, {"arrival": "1933", "distance": 3043, "arrival_delay": 14, "duration": 430, "number": "2287", "departure": "1523", "cancelled": 0, "carrier": "AA", "date": "2015-06-16", "departure_delay": -2}, {"arrival": "1919", "distance": 3043, "arrival_delay": 0, "duration": 395, "number": "2287", "departure": "1544", "cancelled": 0, "carrier": "AA", "date": "2015-06-17", "departure_delay": 19}, {"arrival": "1908", "distance": 3043, "arrival_delay": -11, "duration": 397, "number": "2287", "departure": "1531", "cancelled": 0, "carrier": "AA", "date": "2015-06-18", "departure_delay": 6}, {"arrival": "1906", "distance": 3043, "arrival_delay": -13, "duration": 397, "number": "2287", "departure": "1529", "cancelled": 0, "carrier": "AA", "date": "2015-06-19", "departure_delay": 4}, {"arrival": "1932", "distance": 3043, "arrival_delay": 13, "duration": 415, "number": "2287", "departure": "1537", "cancelled": 0, "carrier": "AA", "date": "2015-06-20", "departure_delay": 12}, {"arrival": "1935", "distance": 3043, "arrival_delay": 16, "duration": 434, "number": "2287", "departure": "1521", "cancelled": 0, "carrier": "AA", "date": "2015-06-21", "departure_delay": -4}, {"arrival": "1913", "distance": 3043, "arrival_delay": -6, "duration": 394, "number": "2287", "departure": "1539", "cancelled": 0, "carrier": "AA", "date": "2015-06-22", "departure_delay": 14}, {"arrival": "1912", "distance": 3043, "arrival_delay": -7, "duration": 400, "number": "2287", "departure": "1532", "cancelled": 0, "carrier": "AA", "date": "2015-06-23", "departure_delay": 7}, {"arrival": "2025", "distance": 3043, "arrival_delay": 66, "duration": 401, "number": "2287", "departure": "1644", "cancelled": 0, "carrier": "AA", "date": "2015-06-24", "departure_delay": 79}, {"arrival": "1940", "distance": 3043, "arrival_delay": 21, "duration": 413, "number": "2287", "departure": "1547", "cancelled": 0, "carrier": "AA", "date": "2015-06-25", "departure_delay": 22}, {"arrival": "1856", "distance": 3043, "arrival_delay": -23, "duration": 392, "number": "2287", "departure": "1524", "cancelled": 0, "carrier": "AA", "date": "2015-06-26", "departure_delay": -1}, {"arrival": "1904", "distance": 3043, "arrival_delay": -15, "duration": 402, "number": "2287", "departure": "1522", "cancelled": 0, "carrier": "AA", "date": "2015-06-27", "departure_delay": -3}, {"arrival": "1901", "distance": 3043, "arrival_delay": -18, "duration": 401, "number": "2287", "departure": "1520", "cancelled": 0, "carrier": "AA", "date": "2015-06-28", "departure_delay": -5}, {"arrival": "1908", "distance": 3043, "arrival_delay": -11, "duration": 402, "number": "2287", "departure": "1526", "cancelled": 0, "carrier": "AA", "date": "2015-06-29", "departure_delay": 1}, {"arrival": "1859", "distance": 3043, "arrival_delay": -20, "duration": 398, "number": "2287", "departure": "1521", "cancelled": 0, "carrier": "AA", "date": "2015-06-30", "departure_delay": -4}, {"arrival": "2008", "distance": 3043, "arrival_delay": 49, "duration": 413, "number": "2287", "departure": "1615", "cancelled": 0, "carrier": "AA", "date": "2015-07-01", "departure_delay": 50}, {"arrival": "2007", "distance": 3043, "arrival_delay": 48, "duration": 408, "number": "2287", "departure": "1619", "cancelled": 0, "carrier": "AA", "date": "2015-07-02", "departure_delay": 54}, {"arrival": "1943", "distance": 3043, "arrival_delay": 24, "duration": 425, "number": "2287", "departure": "1538", "cancelled": 0, "carrier": "AA", "date": "2015-07-03", "departure_delay": 13}, {"arrival": "1916", "distance": 3043, "arrival_delay": -3, "duration": 412, "number": "2287", "departure": "1524", "cancelled": 0, "carrier": "AA", "date": "2015-07-04", "departure_delay": -1}, {"arrival": "2038", "distance": 3043, "arrival_delay": 79, "duration": 398, "number": "2287", "departure": "1700", "cancelled": 0, "carrier": "AA", "date": "2015-07-05", "departure_delay": 95}, {"arrival": "1921", "distance": 3043, "arrival_delay": -3, "duration": 406, "number": "2287", "departure": "1535", "cancelled": 0, "carrier": "AA", "date": "2015-07-06", "departure_delay": 5}, {"arrival": "2040", "distance": 3043, "arrival_delay": 76, "duration": 411, "number": "2287", "departure": "1649", "cancelled": 0, "carrier": "AA", "date": "2015-07-07", "departure_delay": 79}, {"arrival": "1924", "distance": 3043, "arrival_delay": 0, "duration": 401, "number": "2287", "departure": "1543", "cancelled": 0, "carrier": "AA", "date": "2015-07-08", "departure_delay": 13}, {"arrival": "1902", "distance": 3043, "arrival_delay": -22, "duration": 395, "number": "2287", "departure": "1527", "cancelled": 0, "carrier": "AA", "date": "2015-07-09", "departure_delay": -3}, {"arrival": "1849", "distance": 3043, "arrival_delay": -35, "duration": 380, "number": "2287", "departure": "1529", "cancelled": 0, "carrier": "AA", "date": "2015-07-10", "departure_delay": -1}, {"arrival": "1854", "distance": 3043, "arrival_delay": -30, "duration": 385, "number": "2287", "departure": "1529", "cancelled": 0, "carrier": "AA", "date": "2015-07-11", "departure_delay": -1}, {"arrival": "1902", "distance": 3043, "arrival_delay": -22, "duration": 390, "number": "2287", "departure": "1532", "cancelled": 0, "carrier": "AA", "date": "2015-07-12", "departure_delay": 2}, {"arrival": "1851", "distance": 3043, "arrival_delay": -33, "duration": 385, "number": "2287", "departure": "1526", "cancelled": 0, "carrier": "AA", "date": "2015-07-13", "departure_delay": -4}, {"arrival": "1853", "distance": 3043, "arrival_delay": -31, "duration": 383, "number": "2287", "departure": "1530", "cancelled": 0, "carrier": "AA", "date": "2015-07-14", "departure_delay": 0}, {"arrival": "2016", "distance": 3043, "arrival_delay": 52, "duration": 389, "number": "2287", "departure": "1647", "cancelled": 0, "carrier": "AA", "date": "2015-07-15", "departure_delay": 77}, {"arrival": "2036", "distance": 3043, "arrival_delay": 72, "duration": 419, "number": "2287", "departure": "1637", "cancelled": 0, "carrier": "AA", "date": "2015-07-16", "departure_delay": 67}, {"arrival": "1952", "distance": 3043, "arrival_delay": 28, "duration": 416, "number": "2287", "departure": "1556", "cancelled": 0, "carrier": "AA", "date": "2015-07-17", "departure_delay": 26}, {"arrival": "2041", "distance": 3043, "arrival_delay": 77, "duration": 407, "number": "2287", "departure": "1654", "cancelled": 0, "carrier": "AA", "date": "2015-07-18", "departure_delay": 84}, {"arrival": "1954", "distance": 3043, "arrival_delay": 30, "duration": 394, "number": "2287", "departure": "1620", "cancelled": 0, "carrier": "AA", "date": "2015-07-19", "departure_delay": 50}, {"arrival": "1914", "distance": 3043, "arrival_delay": -10, "duration": 402, "number": "2287", "departure": "1532", "cancelled": 0, "carrier": "AA", "date": "2015-07-20", "departure_delay": 2}, {"arrival": "1923", "distance": 3043, "arrival_delay": -1, "duration": 404, "number": "2287", "departure": "1539", "cancelled": 0, "carrier": "AA", "date": "2015-07-21", "departure_delay": 9}, {"arrival": "2127", "distance": 3043, "arrival_delay": 123, "duration": 415, "number": "2287", "departure": "1732", "cancelled": 0, "carrier": "AA", "date": "2015-07-22", "departure_delay": 122}, {"arrival": "2150", "distance": 3043, "arrival_delay": 146, "duration": 398, "number": "2287", "departure": "1812", "cancelled": 0, "carrier": "AA", "date": "2015-07-23", "departure_delay": 162}, {"arrival": "1906", "distance": 3043, "arrival_delay": -18, "duration": 393, "number": "2287", "departure": "1533", "cancelled": 0, "carrier": "AA", "date": "2015-07-24", "departure_delay": 3}, {"arrival": "1917", "distance": 3043, "arrival_delay": -7, "duration": 402, "number": "2287", "departure": "1535", "cancelled": 0, "carrier": "AA", "date": "2015-07-25", "departure_delay": 5}, {"arrival": "1923", "distance": 3043, "arrival_delay": -1, "duration": 408, "number": "2287", "departure": "1535", "cancelled": 0, "carrier": "AA", "date": "2015-07-26", "departure_delay": 5}, {"arrival": "1855", "distance": 3043, "arrival_delay": -29, "duration": 388, "number": "2287", "departure": "1527", "cancelled": 0, "carrier": "AA", "date": "2015-07-27", "departure_delay": -3}, {"arrival": "1907", "distance": 3043, "arrival_delay": -17, "duration": 400, "number": "2287", "departure": "1527", "cancelled": 0, "carrier": "AA", "date": "2015-07-28", "departure_delay": -3}, {"arrival": "1914", "distance": 3043, "arrival_delay": -10, "duration": 403, "number": "2287", "departure": "1531", "cancelled": 0, "carrier": "AA", "date": "2015-07-29", "departure_delay": 1}, {"arrival": "1914", "distance": 3043, "arrival_delay": -10, "duration": 405, "number": "2287", "departure": "1529", "cancelled": 0, "carrier": "AA", "date": "2015-07-30", "departure_delay": -1}, {"arrival": "1934", "distance": 3043, "arrival_delay": 10, "duration": 422, "number": "2287", "departure": "1532", "cancelled": 0, "carrier": "AA", "date": "2015-07-31", "departure_delay": 2}, {"arrival": "2244", "distance": 3043, "arrival_delay": 200, "duration": 420, "number": "2287", "departure": "1844", "cancelled": 0, "carrier": "AA", "date": "2015-08-01", "departure_delay": 194}, {"arrival": "1918", "distance": 3043, "arrival_delay": -6, "duration": 399, "number": "2287", "departure": "1539", "cancelled": 0, "carrier": "AA", "date": "2015-08-02", "departure_delay": 9}, {"arrival": "1925", "distance": 3043, "arrival_delay": 1, "duration": 393, "number": "2287", "departure": "1552", "cancelled": 0, "carrier": "AA", "date": "2015-08-03", "departure_delay": 22}, {"arrival": "1939", "distance": 3043, "arrival_delay": 15, "duration": 406, "number": "2287", "departure": "1553", "cancelled": 0, "carrier": "AA", "date": "2015-08-04", "departure_delay": 23}, {"arrival": "1902", "distance": 3043, "arrival_delay": -22, "duration": 395, "number": "2287", "departure": "1527", "cancelled": 0, "carrier": "AA", "date": "2015-08-05", "departure_delay": -3}, {"arrival": "1923", "distance": 3043, "arrival_delay": -1, "duration": 411, "number": "2287", "departure": "1532", "cancelled": 0, "carrier": "AA", "date": "2015-08-06", "departure_delay": 2}, {"arrival": "1929", "distance": 3043, "arrival_delay": 5, "duration": 394, "number": "2287", "departure": "1555", "cancelled": 0, "carrier": "AA", "date": "2015-08-07", "departure_delay": 25}, {"arrival": "1907", "distance": 3043, "arrival_delay": -17, "duration": 395, "number": "2287", "departure": "1532", "cancelled": 0, "carrier": "AA", "date": "2015-08-08", "departure_delay": 2}, {"arrival": "1950", "distance": 3043, "arrival_delay": 26, "duration": 404, "number": "2287", "departure": "1606", "cancelled": 0, "carrier": "AA", "date": "2015-08-09", "departure_delay": 36}, {"arrival": "2014", "distance": 3043, "arrival_delay": 50, "duration": 407, "number": "2287", "departure": "1627", "cancelled": 0, "carrier": "AA", "date": "2015-08-10", "departure_delay": 57}, {"arrival": "1917", "distance": 3043, "arrival_delay": -7, "duration": 410, "number": "2287", "departure": "1527", "cancelled": 0, "carrier": "AA", "date": "2015-08-11", "departure_delay": -3}, {"arrival": "1950", "distance": 3043, "arrival_delay": 26, "duration": 390, "number": "2287", "departure": "1620", "cancelled": 0, "carrier": "AA", "date": "2015-08-12", "departure_delay": 50}, {"arrival": "2011", "distance": 3043, "arrival_delay": 47, "duration": 403, "number": "2287", "departure": "1628", "cancelled": 0, "carrier": "AA", "date": "2015-08-13", "departure_delay": 58}, {"arrival": "1920", "distance": 3043, "arrival_delay": -4, "duration": 398, "number": "2287", "departure": "1542", "cancelled": 0, "carrier": "AA", "date": "2015-08-14", "departure_delay": 12}, {"arrival": "1937", "distance": 3043, "arrival_delay": 13, "duration": 393, "number": "2287", "departure": "1604", "cancelled": 0, "carrier": "AA", "date": "2015-08-15", "departure_delay": 34}, {"arrival": "1944", "distance": 3043, "arrival_delay": 20, "duration": 417, "number": "2287", "departure": "1547", "cancelled": 0, "carrier": "AA", "date": "2015-08-16", "departure_delay": 17}, {"arrival": "1949", "distance": 3043, "arrival_delay": 25, "duration": 432, "number": "2287", "departure": "1537", "cancelled": 0, "carrier": "AA", "date": "2015-08-17", "departure_delay": 7}, {"arrival": "1932", "distance": 3043, "arrival_delay": 8, "duration": 424, "number": "2287", "departure": "1528", "cancelled": 0, "carrier": "AA", "date": "2015-08-18", "departure_delay": -2}, {"arrival": "1956", "distance": 3043, "arrival_delay": 32, "duration": 436, "number": "2287", "departure": "1540", "cancelled": 0, "carrier": "AA", "date": "2015-08-19", "departure_delay": 10}, {"arrival": "1914", "distance": 3043, "arrival_delay": -10, "duration": 406, "number": "2287", "departure": "1528", "cancelled": 0, "carrier": "AA", "date": "2015-08-20", "departure_delay": -2}, {"arrival": "1927", "distance": 3043, "arrival_delay": 3, "duration": 405, "number": "2287", "departure": "1542", "cancelled": 0, "carrier": "AA", "date": "2015-08-21", "departure_delay": 12}, {"arrival": "1926", "distance": 3043, "arrival_delay": 2, "duration": 417, "number": "2287", "departure": "1529", "cancelled": 0, "carrier": "AA", "date": "2015-08-22", "departure_delay": -1}, {"arrival": "1906", "distance": 3043, "arrival_delay": -18, "duration": 400, "number": "2287", "departure": "1526", "cancelled": 0, "carrier": "AA", "date": "2015-08-23", "departure_delay": -4}, {"arrival": "1939", "distance": 3043, "arrival_delay": 15, "duration": 419, "number": "2287", "departure": "1540", "cancelled": 0, "carrier": "AA", "date": "2015-08-24", "departure_delay": 10}, {"arrival": "1925", "distance": 3043, "arrival_delay": 1, "duration": 408, "number": "2287", "departure": "1537", "cancelled": 0, "carrier": "AA", "date": "2015-08-25", "departure_delay": 7}, {"arrival": "1946", "distance": 3043, "arrival_delay": 22, "duration": 412, "number": "2287", "departure": "1554", "cancelled": 0, "carrier": "AA", "date": "2015-08-26", "departure_delay": 24}, {"arrival": "2012", "distance": 3043, "arrival_delay": 48, "duration": 423, "number": "2287", "departure": "1609", "cancelled": 0, "carrier": "AA", "date": "2015-08-27", "departure_delay": 39}, {"arrival": "1906", "distance": 3043, "arrival_delay": -18, "duration": 397, "number": "2287", "departure": "1529", "cancelled": 0, "carrier": "AA", "date": "2015-08-28", "departure_delay": -1}, {"arrival": "1902", "distance": 3043, "arrival_delay": -22, "duration": 396, "number": "2287", "departure": "1526", "cancelled": 0, "carrier": "AA", "date": "2015-08-29", "departure_delay": -4}, {"arrival": "1859", "distance": 3043, "arrival_delay": -25, "duration": 397, "number": "2287", "departure": "1522", "cancelled": 0, "carrier": "AA", "date": "2015-08-30", "departure_delay": -8}, {"arrival": "1911", "distance": 3043, "arrival_delay": -13, "duration": 403, "number": "2287", "departure": "1528", "cancelled": 0, "carrier": "AA", "date": "2015-08-31", "departure_delay": -2}, {"arrival": "1909", "distance": 3043, "arrival_delay": -15, "duration": 397, "number": "2287", "departure": "1532", "cancelled": 0, "carrier": "AA", "date": "2015-09-01", "departure_delay": 2}, {"arrival": "1905", "distance": 3043, "arrival_delay": -19, "duration": 395, "number": "2287", "departure": "1530", "cancelled": 0, "carrier": "AA", "date": "2015-09-02", "departure_delay": 0}, {"arrival": "1907", "distance": 3043, "arrival_delay": -17, "duration": 390, "number": "2287", "departure": "1537", "cancelled": 0, "carrier": "AA", "date": "2015-09-03", "departure_delay": 7}, {"arrival": "1905", "distance": 3043, "arrival_delay": -19, "duration": 396, "number": "2287", "departure": "1529", "cancelled": 0, "carrier": "AA", "date": "2015-09-04", "departure_delay": -1}, {"arrival": "1905", "distance": 3043, "arrival_delay": -19, "duration": 384, "number": "2287", "departure": "1541", "cancelled": 0, "carrier": "AA", "date": "2015-09-05", "departure_delay": 11}, {"arrival": "1854", "distance": 3043, "arrival_delay": -30, "duration": 390, "number": "2287", "departure": "1524", "cancelled": 0, "carrier": "AA", "date": "2015-09-06", "departure_delay": -6}, {"arrival": "1918", "distance": 3043, "arrival_delay": -6, "duration": 404, "number": "2287", "departure": "1534", "cancelled": 0, "carrier": "AA", "date": "2015-09-07", "departure_delay": 4}, {"arrival": "2014", "distance": 3043, "arrival_delay": 50, "duration": 422, "number": "2287", "departure": "1612", "cancelled": 0, "carrier": "AA", "date": "2015-09-08", "departure_delay": 42}, {"arrival": "2025", "distance": 3043, "arrival_delay": 67, "duration": 413, "number": "2287", "departure": "1632", "cancelled": 0, "carrier": "AA", "date": "2015-09-09", "departure_delay": 62}, {"arrival": "1918", "distance": 3043, "arrival_delay": 0, "duration": 413, "number": "2287", "departure": "1525", "cancelled": 0, "carrier": "AA", "date": "2015-09-10", "departure_delay": -5}, {"arrival": "1919", "distance": 3043, "arrival_delay": 1, "duration": 411, "number": "2287", "departure": "1528", "cancelled": 0, "carrier": "AA", "date": "2015-09-11", "departure_delay": -2}, {"arrival": "1901", "distance": 3043, "arrival_delay": -17, "duration": 398, "number": "2287", "departure": "1523", "cancelled": 0, "carrier": "AA", "date": "2015-09-12", "departure_delay": -7}, {"arrival": "1912", "distance": 3043, "arrival_delay": -6, "duration": 405, "number": "2287", "departure": "1527", "cancelled": 0, "carrier": "AA", "date": "2015-09-13", "departure_delay": -3}, {"arrival": "1922", "distance": 3043, "arrival_delay": 4, "duration": 399, "number": "2287", "departure": "1543", "cancelled": 0, "carrier": "AA", "date": "2015-09-14", "departure_delay": 13}, {"arrival": "1857", "distance": 3043, "arrival_delay": -21, "duration": 391, "number": "2287", "departure": "1526", "cancelled": 0, "carrier": "AA", "date": "2015-09-15", "departure_delay": -4}, {"arrival": "1909", "distance": 3043, "arrival_delay": -9, "duration": 401, "number": "2287", "departure": "1528", "cancelled": 0, "carrier": "AA", "date": "2015-09-16", "departure_delay": -2}, {"arrival": "1927", "distance": 3043, "arrival_delay": 9, "duration": 413, "number": "2287", "departure": "1534", "cancelled": 0, "carrier": "AA", "date": "2015-09-17", "departure_delay": 4}, {"arrival": "1914", "distance": 3043, "arrival_delay": -4, "duration": 411, "number": "2287", "departure": "1523", "cancelled": 0, "carrier": "AA", "date": "2015-09-18", "departure_delay": -7}, {"arrival": "1930", "distance": 3043, "arrival_delay": 12, "duration": 421, "number": "2287", "departure": "1529", "cancelled": 0, "carrier": "AA", "date": "2015-09-19", "departure_delay": -1}, {"arrival": "1922", "distance": 3043, "arrival_delay": 4, "duration": 419, "number": "2287", "departure": "1523", "cancelled": 0, "carrier": "AA", "date": "2015-09-20", "departure_delay": -7}, {"arrival": "1911", "distance": 3043, "arrival_delay": -7, "duration": 399, "number": "2287", "departure": "1532", "cancelled": 0, "carrier": "AA", "date": "2015-09-21", "departure_delay": 2}, {"arrival": "2015", "distance": 3043, "arrival_delay": 57, "duration": 392, "number": "2287", "departure": "1643", "cancelled": 0, "carrier": "AA", "date": "2015-09-22", "departure_delay": 73}, {"arrival": "1905", "distance": 3043, "arrival_delay": -13, "duration": 402, "number": "2287", "departure": "1523", "cancelled": 0, "carrier": "AA", "date": "2015-09-23", "departure_delay": -7}, {"arrival": "1918", "distance": 3043, "arrival_delay": 0, "duration": 409, "number": "2287", "departure": "1529", "cancelled": 0, "carrier": "AA", "date": "2015-09-24", "departure_delay": -1}, {"arrival": "2049", "distance": 3043, "arrival_delay": 91, "duration": 428, "number": "2287", "departure": "1641", "cancelled": 0, "carrier": "AA", "date": "2015-09-25", "departure_delay": 71}, {"arrival": "1932", "distance": 3043, "arrival_delay": 14, "duration": 425, "number": "2287", "departure": "1527", "cancelled": 0, "carrier": "AA", "date": "2015-09-26", "departure_delay": -3}, {"arrival": "2019", "distance": 3043, "arrival_delay": 61, "duration": 408, "number": "2287", "departure": "1631", "cancelled": 0, "carrier": "AA", "date": "2015-09-27", "departure_delay": 61}, {"arrival": "1931", "distance": 3043, "arrival_delay": 13, "duration": 427, "number": "2287", "departure": "1524", "cancelled": 0, "carrier": "AA", "date": "2015-09-28", "departure_delay": -6}, {"arrival": "1922", "distance": 3043, "arrival_delay": 4, "duration": 414, "number": "2287", "departure": "1528", "cancelled": 0, "carrier": "AA", "date": "2015-09-29", "departure_delay": -2}, {"arrival": "1915", "distance": 3043, "arrival_delay": -3, "duration": 409, "number": "2287", "departure": "1526", "cancelled": 0, "carrier": "AA", "date": "2015-09-30", "departure_delay": -4}, {"arrival": "1932", "distance": 3043, "arrival_delay": 14, "duration": 415, "number": "2287", "departure": "1537", "cancelled": 0, "carrier": "AA", "date": "2015-10-01", "departure_delay": 7}, {"arrival": "1937", "distance": 3043, "arrival_delay": 19, "duration": 421, "number": "2287", "departure": "1536", "cancelled": 0, "carrier": "AA", "date": "2015-10-02", "departure_delay": 6}, {"arrival": "2024", "distance": 3043, "arrival_delay": 66, "duration": 410, "number": "2287", "departure": "1634", "cancelled": 0, "carrier": "AA", "date": "2015-10-03", "departure_delay": 64}, {"arrival": "1926", "distance": 3043, "arrival_delay": 8, "duration": 417, "number": "2287", "departure": "1529", "cancelled": 0, "carrier": "AA", "date": "2015-10-04", "departure_delay": -1}]}]}
