{"results": [{"code": "DL1545", "data": [{"arrival": "1557", "distance": 596, "arrival_delay": -13, "duration": 101, "number": "1545", "departure": "1416", "cancelled": 0, "carrier": "DL", "date": "2015-06-02", "departure_delay": 1}]}, {"code": "DL516", "data": [{"arrival": "1548", "distance": 596, "arrival_delay": -17, "duration": 94, "number": "516", "departure": "1414", "cancelled": 0, "carrier": "DL", "date": "2015-06-05", "departure_delay": -1}]}, {"code": "DL2313", "data": [{"arrival": "1046", "distance": 596, "arrival_delay": -26, "duration": 99, "number": "2313", "departure": "0907", "cancelled": 0, "carrier": "DL", "date": "2015-06-02", "departure_delay": -5}]}]}
