{"results": [{"code": "AA1816", "data": [{"arrival": "1350", "distance": 482, "arrival_delay": -14, "duration": 88, "number": "1816", "departure": "1222", "cancelled": 0, "carrier": "AA", "date": "2015-08-18", "departure_delay": -3}, {"arrival": "1344", "distance": 482, "arrival_delay": -20, "duration": 87, "number": "1816", "departure": "1217", "cancelled": 0, "carrier": "AA", "date": "2015-08-19", "departure_delay": -8}, {"arrival": "1405", "distance": 482, "arrival_delay": 1, "duration": 100, "number": "1816", "departure": "1225", "cancelled": 0, "carrier": "AA", "date": "2015-08-20", "departure_delay": 0}, {"arrival": "1411", "distance": 482, "arrival_delay": 7, "duration": 106, "number": "1816", "departure": "1225", "cancelled": 0, "carrier": "AA", "date": "2015-08-21", "departure_delay": 0}, {"arrival": "1346", "distance": 482, "arrival_delay": -18, "duration": 85, "number": "1816", "departure": "1221", "cancelled": 0, "carrier": "AA", "date": "2015-08-22", "departure_delay": -4}, {"arrival": "1356", "distance": 482, "arrival_delay": -8, "duration": 97, "number": "1816", "departure": "1219", "cancelled": 0, "carrier": "AA", "date": "2015-08-23", "departure_delay": -6}, {"arrival": "1357", "distance": 482, "arrival_delay": -7, "duration": 94, "number": "1816", "departure": "1223", "cancelled": 0, "carrier": "AA", "date": "2015-08-24", "departure_delay": -2}, {"arrival": "1349", "distance": 482, "arrival_delay": -15, "duration": 92, "number": "1816", "departure": "1217", "cancelled": 0, "carrier": "AA", "date": "2015-08-25", "departure_delay": -8}, {"arrival": "1406", "distance": 482, "arrival_delay": 2, "duration": 106, "number": "1816", "departure": "1220", "cancelled": 0, "carrier": "AA", "date": "2015-08-26", "departure_delay": -5}, {"arrival": "1404", "distance": 482, "arrival_delay": 0, "duration": 103, "number": "1816", "departure": "1221", "cancelled": 0, "carrier": "AA", "date": "2015-08-27", "departure_delay": -4}, {"arrival": "1418", "distance": 482, "arrival_delay": 14, "duration": 117, "number": "1816", "departure": "1221", "cancelled": 0, "carrier": "AA", "date": "2015-08-28", "departure_delay": -4}, {"arrival": "1400", "distance": 482, "arrival_delay": -4, "duration": 105, "number": "1816", "departure": "1215", "cancelled": 0, "carrier": "AA", "date": "2015-08-29", "departure_delay": -10}, {"arrival": "1537", "distance": 482, "arrival_delay": 93, "duration": 92, "number": "1816", "departure": "1405", "cancelled": 0, "carrier": "AA", "date": "2015-08-30", "departure_delay": 100}, {"arrival": "1357", "distance": 482, "arrival_delay": -7, "duration": 97, "number": "1816", "departure": "1220", "cancelled": 0, "carrier": "AA", "date": "2015-08-31", "departure_delay": -5}, {"arrival": "", "distance": 482, "arrival_delay": 0, "duration": 0, "number": "1816", "departure": "", "cancelled": 1, "carrier": "AA", "date": "2015-09-01", "departure_delay": 0}, {"arrival": "1353", "distance": 482, "arrival_delay": -11, "duration": 96, "number": "1816", "departure": "1217", "cancelled": 0, "carrier": "AA", "date": "2015-09-02", "departure_delay": -8}, {"arrival": "1404", "distance": 482, "arrival_delay": 0, "duration": 108, "number": "1816", "departure": "1216", "cancelled": 0, "carrier": "AA", "date": "2015-09-03", "departure_delay": -9}, {"arrival": "1349", "distance": 482, "arrival_delay": -15, "duration": 94, "number": "1816", "departure": "1215", "cancelled": 0, "carrier": "AA", "date": "2015-09-04", "departure_delay": -10}, {"arrival": "1350", "distance": 482, "arrival_delay": -14, "duration": 84, "number": "1816", "departure": "1226", "cancelled": 0, "carrier": "AA", "date": "2015-09-05", "departure_delay": 1}, {"arrival": "1357", "distance": 482, "arrival_delay": -7, "duration": 95, "number": "1816", "departure": "1222", "cancelled": 0, "carrier": "AA", "date": "2015-09-07", "departure_delay": -3}, {"arrival": "1417", "distance": 482, "arrival_delay": 13, "duration": 116, "number": "1816", "departure": "1221", "cancelled": 0, "carrier": "AA", "date": "2015-09-08", "departure_delay": -4}, {"arrival": "1555", "distance": 482, "arrival_delay": -6, "duration": 97, "number": "1816", "departure": "1418", "cancelled": 0, "carrier": "AA", "date": "2015-09-09", "departure_delay": -2}, {"arrival": "1746", "distance": 482, "arrival_delay": 105, "duration": 95, "number": "1816", "departure": "1611", "cancelled": 0, "carrier": "AA", "date": "2015-09-10", "departure_delay": 111}, {"arrival": "1545", "distance": 482, "arrival_delay": -16, "duration": 91, "number": "1816", "departure": "1414", "cancelled": 0, "carrier": "AA", "date": "2015-09-11", "departure_delay": -6}, {"arrival": "1426", "distance": 482, "arrival_delay": 20, "duration": 127, "number": "1816", "departure": "1219", "cancelled": 0, "carrier": "AA", "date": "2015-09-12", "departure_delay": -6}, {"arrival": "1410", "distance": 482, "arrival_delay": 4, "duration": 109, "number": "1816", "departure": "1221", "cancelled": 0, "carrier": "AA", "date": "2015-09-13", "departure_delay": -4}, {"arrival": "1606", "distance": 482, "arrival_delay": 5, "duration": 109, "number": "1816", "departure": "1417", "cancelled": 0, "carrier": "AA", "date": "2015-09-14", "departure_delay": -3}, {"arrival": "1550", "distance": 482, "arrival_delay": -11, "duration": 92, "number": "1816", "departure": "1418", "cancelled": 0, "carrier": "AA", "date": "2015-09-15", "departure_delay": -2}, {"arrival": "", "distance": 482, "arrival_delay": 0, "duration": 0, "number": "1816", "departure": "", "cancelled": 1, "carrier": "AA", "date": "2015-09-16", "departure_delay": 0}, {"arrival": "1554", "distance": 482, "arrival_delay": -7, "duration": 93, "number": "1816", "departure": "1421", "cancelled": 0, "carrier": "AA", "date": "2015-09-17", "departure_delay": 1}, {"arrival": "1547", "distance": 482, "arrival_delay": -14, "duration": 86, "number": "1816", "departure": "1421", "cancelled": 0, "carrier": "AA", "date": "2015-09-18", "departure_delay": 1}, {"arrival": "1443", "distance": 482, "arrival_delay": 37, "duration": 88, "number": "1816", "departure": "1315", "cancelled": 0, "carrier": "AA", "date": "2015-09-19", "departure_delay": 50}, {"arrival": "1436", "distance": 482, "arrival_delay": 30, "duration": 96, "number": "1816", "departure": "1300", "cancelled": 0, "carrier": "AA", "date": "2015-09-20", "departure_delay": 35}, {"arrival": "1556", "distance": 482, "arrival_delay": -5, "duration": 100, "number": "1816", "departure": "1416", "cancelled": 0, "carrier": "AA", "date": "2015-09-21", "departure_delay": -4}, {"arrival": "1601", "distance": 482, "arrival_delay": 0, "duration": 94, "number": "1816", "departure": "1427", "cancelled": 0, "carrier": "AA", "date": "2015-09-22", "departure_delay": 7}, {"arrival": "1540", "distance": 482, "arrival_delay": -21, "duration": 88, "number": "1816", "departure": "1412", "cancelled": 0, "carrier": "AA", "date": "2015-09-23", "departure_delay": -8}, {"arrival": "1537", "distance": 482, "arrival_delay": -24, "duration": 88, "number": "1816", "departure": "1409", "cancelled": 0, "carrier": "AA", "date": "2015-09-24", "departure_delay": -11}, {"arrival": "1547", "distance": 482, "arrival_delay": -14, "duration": 93, "number": "1816", "departure": "1414", "cancelled": 0, "carrier": "AA", "date": "2015-09-25", "departure_delay": -6}, {"arrival": "1357", "distance": 482, "arrival_delay": -9, "duration": 92, "number": "1816", "departure": "1225", "cancelled": 0, "carrier": "AA", "date": "2015-09-26", "departure_delay": 0}, {"arrival": "1409", "distance": 482, "arrival_delay": 3, "duration": 109, "number": "1816", "departure": "1220", "cancelled": 0, "carrier": "AA", "date": "2015-09-27", "departure_delay": -5}, {"arrival": "1550", "distance": 482, "arrival_delay": -11, "duration": 92, "number": "1816", "departure": "1418", "cancelled": 0, "carrier": "AA", "date": "2015-09-28", "departure_delay": -2}, {"arrival": "1559", "distance": 482, "arrival_delay": -2, "duration": 98, "number": "1816", "departure": "1421", "cancelled": 0, "carrier": "AA", "date": "2015-09-29", "departure_delay": 1}, {"arrival": "1604", "distance": 482, "arrival_delay": 3, "duration": 103, "number": "1816", "departure": "1421", "cancelled": 0, "carrier": "AA", "date": "2015-09-30", "departure_delay": 1}, {"arrival": "1600", "distance": 482, "arrival_delay": -1, "duration": 105, "number": "1816", "departure": "1415", "cancelled": 0, "carrier": "AA", "date": "2015-10-01", "departure_delay": -5}, {"arrival": "1612", "distance": 482, "arrival_delay": 11, "duration": 116, "number": "1816", "departure": "1416", "cancelled": 0, "carrier": "AA", "date": "2015-10-02", "departure_delay": -4}, {"arrival": "1359", "distance": 482, "arrival_delay": -7, "duration": 100, "number": "1816", "departure": "1219", "cancelled": 0, "carrier": "AA", "date": "2015-10-03", "departure_delay": -6}, {"arrival": "1344", "distance": 482, "arrival_delay": -22, "duration": 84, "number": "1816", "departure": "1220", "cancelled": 0, "carrier": "AA", "date": "2015-10-04", "departure_delay": -5}]}]}
