{"results": [{"code": "UA1142", "data": [{"arrival": "0810", "distance": 667, "arrival_delay": -3, "duration": 120, "number": "1142", "departure": "0610", "cancelled": 0, "carrier": "UA", "date": "2015-10-05", "departure_delay": 0}, {"arrival": "0823", "distance": 667, "arrival_delay": 10, "duration": 111, "number": "1142", "departure": "0632", "cancelled": 0, "carrier": "UA", "date": "2015-10-12", "departure_delay": 22}]}, {"code": "UA1424", "data": [{"arrival": "0819", "distance": 667, "arrival_delay": 16, "duration": 132, "number": "1424", "departure": "0607", "cancelled": 0, "carrier": "UA", "date": "2015-08-24", "departure_delay": 7}]}]}
